[{"station": "GAMELJNE", "number": "104221"}, {"station": "Rašica", "number": "104211"}, {"station": "Zg. Gameljne", "number": "104201"}, {"station": "Šmartno", "number": "104191"}, {"station": "Tacen", "number": "804151"}, {"station": "Tacenski most", "number": "804141"}, {"station": "Ob daljnovodu", "number": "804111"}, {"station": "Tabor", "number": "804101"}, {"station": "Na klancu", "number": "804091"}, {"station": "Kosmačeva", "number": "804081"}, {"station": "Šentvid", "number": "804041"}, {"station": "Podgora", "number": "804031"}, {"station": "Prušnikova", "number": "804021"}, {"station": "IMP", "number": "804161"}, {"station": "Tehnounion", "number": "803071"}, {"station": "Ljubljanske brigade", "number": "803061"}, {"station": "Litostrojska", "number": "803051"}, {"station": "Slovenija avto", "number": "803011"}, {"station": "Kino Šiška", "number": "802021"}, {"station": "Stara cerkev", "number": "802011"}, {"station": "Tivoli", "number": "801011"}, {"station": "Gosposvetska", "number": "700011"}, {"station": "Bavarski dvor (Korabar)", "number": "600011"}, {"station": "Razstavišče", "number": "100022"}, {"station": "Astra", "number": "101052"}, {"station": "Stadion", "number": "102042"}, {"station": "Mercator", "number": "102082"}, {"station": "AMZS", "number": "103032"}, {"station": "Smelt", "number": "103072"}, {"station": "Stožice", "number": "103102"}, {"station": "Ruski car", "number": "103132"}, {"station": "Ježica", "number": "104032"}, {"station": "Sava", "number": "104054"}, {"station": "Elma", "number": "104062"}, {"station": "Šlandrova", "number": "104072"}, {"station": "Obrtna cona", "number": "104082"}, {"station": "Cesta na Brod", "number": "104092"}, {"station": "Slovenijales", "number": "204112"}, {"station": "BRNČIČEVA", "number": "204121"}]